wetlands/environment.py
wetlands/environment_manager.py
wetlands/external_environment.py
wetlands/internal_environment.py
wetlands/logger.py
wetlands/main.py
wetlands/module_executor.py
wetlands/ndarray.py
wetlands/_internal/command_executor.py
wetlands/_internal/command_generator.py
wetlands/_internal/config_parser.py
wetlands/_internal/dependency_manager.py
wetlands/_internal/exceptions.py
wetlands/_internal/install.py
wetlands/_internal/process_logger.py
wetlands/_internal/settings_manager.py
wetlands/_internal/checksums/micromamba-linux-64.sha256
wetlands/_internal/checksums/micromamba-linux-aarch64.sha256
wetlands/_internal/checksums/micromamba-linux-ppc64le.sha256
wetlands/_internal/checksums/micromamba-osx-64.sha256
wetlands/_internal/checksums/micromamba-osx-arm64.sha256
wetlands/_internal/checksums/micromamba-win-64.sha256
wetlands/_internal/checksums/pixi-aarch64-apple-darwin.tar.gz.sha256
wetlands/_internal/checksums/pixi-aarch64-pc-windows-msvc.zip.sha256
wetlands/_internal/checksums/pixi-aarch64-unknown-linux-musl.tar.gz.sha256
wetlands/_internal/checksums/pixi-x86_64-apple-darwin.tar.gz.sha256
wetlands/_internal/checksums/pixi-x86_64-pc-windows-msvc.zip.sha256
wetlands/_internal/checksums/pixi-x86_64-unknown-linux-musl.tar.gz.sha256
wetlands/_internal/checksums/vc_redist.x64.exe.sha256
wetlands-0.4.11.dist-info/METADATA
wetlands-0.4.11.dist-info/WHEEL
wetlands-0.4.11.dist-info/entry_points.txt
wetlands-0.4.11.dist-info/RECORD
