Metadata-Version: 2.4
Name: wetlands
Version: 0.4.11
Summary: Wetlands is a lightweight library to create conda environment and execute code inside them.
Author-email: Arthur Masson <arthur.masson@inria.fr>
License-Expression: MIT
Classifier: Intended Audience :: Developers
Classifier: Programming Language :: Python :: 3.10
Classifier: Programming Language :: Python :: 3.11
Classifier: Programming Language :: Python :: 3.12
Classifier: Programming Language :: Python :: 3.13
Requires-Python: >=3.10
Requires-Dist: json5>=0.12.1
Requires-Dist: packaging>=24.2
Requires-Dist: psutil>=6.1.0
Requires-Dist: pyyaml>=6.0.2
Requires-Dist: send2trash>=1.8.3
Requires-Dist: tomli>=1.0; python_version < '3.11'
Requires-Dist: typing-extensions>=4.0; python_version < '3.11'
Provides-Extra: debug
Requires-Dist: debugpy>=1.8.17; extra == 'debug'
Requires-Dist: json5>=0.12.1; extra == 'debug'
Provides-Extra: docs
Requires-Dist: mike>=2.1.3; extra == 'docs'
Requires-Dist: mkdocs-gen-files>=0.5.0; extra == 'docs'
Requires-Dist: mkdocs-include-markdown-plugin>=7.1.5; extra == 'docs'
Requires-Dist: mkdocs-literate-nav>=0.6.2; extra == 'docs'
Requires-Dist: mkdocs-material>=9.6.11; extra == 'docs'
Requires-Dist: mkdocstrings[python]>=0.29.1; extra == 'docs'
Provides-Extra: shared-memory
Requires-Dist: numpy>=1.26; extra == 'shared-memory'
